miniwifi/__init__.py
miniwifi/core.py
miniwifi/exceptions.py
miniwifi/utils.py
miniwifi-1.2.0.dist-info/METADATA
miniwifi-1.2.0.dist-info/WHEEL
miniwifi-1.2.0.dist-info/entry_points.txt
miniwifi-1.2.0.dist-info/top_level.txt
miniwifi-1.2.0.dist-info/RECORD
