Metadata-Version: 2.4
Name: miniwifi
Version: 1.2.0
Summary: Python Wi-Fi security toolkit
Home-page: https://github.com/mr-fidal/miniwifi
Author: MrFidal
Author-email: mrfidal@proton.me
License: MIT
Project-URL: Bug Reports, https://github.com/mr-fidal/miniwifi/issues
Project-URL: Source, https://github.com/mr-fidal/miniwifi
Keywords: wifi security networking pentesting
Classifier: Programming Language :: Python :: 3
Classifier: License :: OSI Approved :: MIT License
Classifier: Operating System :: OS Independent
Classifier: Development Status :: 4 - Beta
Classifier: Intended Audience :: Developers
Classifier: Topic :: Security
Classifier: Topic :: System :: Networking
Requires-Python: >=3.7
Requires-Dist: pywifi
Dynamic: author
Dynamic: author-email
Dynamic: classifier
Dynamic: description
Dynamic: description-content-type
Dynamic: home-page
Dynamic: keywords
Dynamic: license
Dynamic: project-url
Dynamic: requires-dist
Dynamic: requires-python
Dynamic: summary
